pywebguard/__init__.py
pywebguard/cli.py
pywebguard/core/__init__.py
pywebguard/core/base.py
pywebguard/core/config.py
pywebguard/core/constants.py
pywebguard/filters/__init__.py
pywebguard/filters/base.py
pywebguard/filters/ip_filter.py
pywebguard/filters/user_agent.py
pywebguard/frameworks/__init__.py
pywebguard/frameworks/_fastapi.py
pywebguard/frameworks/_flask.py
pywebguard/limiters/__init__.py
pywebguard/limiters/base.py
pywebguard/limiters/rate_limit.py
pywebguard/logging/__init__.py
pywebguard/logging/base.py
pywebguard/logging/logger.py
pywebguard/logging/backends/__init__.py
pywebguard/logging/backends/_elasticsearch.py
pywebguard/logging/backends/_meilisearch.py
pywebguard/logging/backends/_mongodb.py
pywebguard/security/__init__.py
pywebguard/security/base.py
pywebguard/security/cors.py
pywebguard/security/penetration.py
pywebguard/storage/__init__.py
pywebguard/storage/_mongodb.py
pywebguard/storage/_postgresql.py
pywebguard/storage/_redis.py
pywebguard/storage/_sqlite.py
pywebguard/storage/_tinydb.py
pywebguard/storage/base.py
pywebguard/storage/memory.py
pywebguard/utils/__init__.py
pywebguard/utils/ip.py
pywebguard/utils/request.py
pywebguard-1.0.26.dist-info/licenses/LICENSE
pywebguard-1.0.26.dist-info/METADATA
pywebguard-1.0.26.dist-info/WHEEL
pywebguard-1.0.26.dist-info/entry_points.txt
pywebguard-1.0.26.dist-info/top_level.txt
pywebguard-1.0.26.dist-info/RECORD
