Metadata-Version: 2.4
Name: pywebguard
Version: 1.0.26
Summary: A comprehensive security library for Python web applications
Home-page: https://github.com/py-daily/pywebguard
Author: py-daily
Author-email: mm@ktechhub.com
Classifier: Development Status :: 3 - Alpha
Classifier: Intended Audience :: Developers
Classifier: License :: OSI Approved :: MIT License
Classifier: Operating System :: OS Independent
Classifier: Programming Language :: Python :: 3.14
Classifier: Programming Language :: Python :: 3.13
Classifier: Programming Language :: Python :: 3.12
Classifier: Programming Language :: Python :: 3.11
Classifier: Programming Language :: Python :: 3.10
Classifier: Programming Language :: Python :: 3.9
Classifier: Programming Language :: Python :: 3.8
Classifier: Programming Language :: Python :: 3
Classifier: Topic :: Security
Classifier: Topic :: Internet :: WWW/HTTP
Classifier: Topic :: Software Development :: Libraries :: Python Modules
Requires-Python: >=3.8
License-File: LICENSE
Requires-Dist: pydantic>=2.0.0
Requires-Dist: ipaddress>=1.0.23
Requires-Dist: python-dotenv>=0.19.0
Provides-Extra: fastapi
Requires-Dist: fastapi>=0.115.12; extra == "fastapi"
Requires-Dist: httpx>=0.28.1; extra == "fastapi"
Requires-Dist: starlette>=0.14.0; extra == "fastapi"
Requires-Dist: uvicorn>=0.34.2; extra == "fastapi"
Provides-Extra: flask
Requires-Dist: flask>=3.1.1; extra == "flask"
Provides-Extra: redis
Requires-Dist: redis>=6.1.0; extra == "redis"
Requires-Dist: aioredis>=2.0.1; extra == "redis"
Provides-Extra: sqlite
Requires-Dist: aiosqlite>=0.21.0; extra == "sqlite"
Provides-Extra: tinydb
Requires-Dist: tinydb>=4.8.2; extra == "tinydb"
Provides-Extra: mongodb
Requires-Dist: pymongo>=4.13.0; extra == "mongodb"
Provides-Extra: postgresql
Requires-Dist: asyncpg>=0.30.0; extra == "postgresql"
Requires-Dist: psycopg2-binary>=2.9.10; extra == "postgresql"
Provides-Extra: elasticsearch
Requires-Dist: elasticsearch>=9.0.1; extra == "elasticsearch"
Provides-Extra: all-storage
Requires-Dist: redis>=6.1.0; extra == "all-storage"
Requires-Dist: aioredis>=2.0.1; extra == "all-storage"
Requires-Dist: aiosqlite>=0.21.0; extra == "all-storage"
Requires-Dist: tinydb>=4.8.2; extra == "all-storage"
Requires-Dist: pymongo>=4.13.0; extra == "all-storage"
Requires-Dist: asyncpg>=0.30.0; extra == "all-storage"
Requires-Dist: psycopg2-binary>=2.9.10; extra == "all-storage"
Requires-Dist: elasticsearch>=9.0.1; extra == "all-storage"
Provides-Extra: all-frameworks
Requires-Dist: fastapi>=0.115.12; extra == "all-frameworks"
Requires-Dist: httpx>=0.28.1; extra == "all-frameworks"
Requires-Dist: starlette>=0.14.0; extra == "all-frameworks"
Requires-Dist: uvicorn>=0.34.2; extra == "all-frameworks"
Requires-Dist: flask>=3.1.1; extra == "all-frameworks"
Provides-Extra: all
Requires-Dist: fastapi>=0.115.12; extra == "all"
Requires-Dist: httpx>=0.28.1; extra == "all"
Requires-Dist: starlette>=0.14.0; extra == "all"
Requires-Dist: uvicorn>=0.34.2; extra == "all"
Requires-Dist: flask>=3.1.1; extra == "all"
Requires-Dist: redis>=6.1.0; extra == "all"
Requires-Dist: aioredis>=2.0.1; extra == "all"
Requires-Dist: aiosqlite>=0.21.0; extra == "all"
Requires-Dist: tinydb>=4.8.2; extra == "all"
Requires-Dist: pymongo>=4.13.0; extra == "all"
Requires-Dist: asyncpg>=0.30.0; extra == "all"
Requires-Dist: psycopg2-binary>=2.9.10; extra == "all"
Requires-Dist: elasticsearch>=9.0.1; extra == "all"
Provides-Extra: dev
Requires-Dist: pytest>=7.0.0; extra == "dev"
Requires-Dist: pytest-cov>=6.1.1; extra == "dev"
Requires-Dist: pytest-asyncio>=0.26.0; extra == "dev"
Requires-Dist: black>=25.1.0; extra == "dev"
Requires-Dist: isort>=6.0.1; extra == "dev"
Requires-Dist: mypy>=1.15.0; extra == "dev"
Requires-Dist: flake8>=7.2.0; extra == "dev"
Dynamic: author
Dynamic: author-email
Dynamic: classifier
Dynamic: description
Dynamic: description-content-type
Dynamic: home-page
Dynamic: license-file
Dynamic: provides-extra
Dynamic: requires-dist
Dynamic: requires-python
Dynamic: summary
